odoo/addons/account_payment_line_import/README.rst
odoo/addons/account_payment_line_import/__init__.py
odoo/addons/account_payment_line_import/__manifest__.py
odoo/addons/account_payment_line_import/data/import_template.xml
odoo/addons/account_payment_line_import/data/payment_detail.xlsx
odoo/addons/account_payment_line_import/i18n/account_payment_line_import.pot
odoo/addons/account_payment_line_import/i18n/es.po
odoo/addons/account_payment_line_import/i18n/it.po
odoo/addons/account_payment_line_import/models/__init__.py
odoo/addons/account_payment_line_import/models/account_payment.py
odoo/addons/account_payment_line_import/readme/CONTRIBUTORS.rst
odoo/addons/account_payment_line_import/readme/DESCRIPTION.rst
odoo/addons/account_payment_line_import/readme/USAGE.rst
odoo/addons/account_payment_line_import/static/description/icon.png
odoo/addons/account_payment_line_import/static/description/index.html
odoo/addons/account_payment_line_import/views/account_payment_view.xml
odoo14_addon_account_payment_line_import-14.0.1.0.1.dev8.dist-info/METADATA
odoo14_addon_account_payment_line_import-14.0.1.0.1.dev8.dist-info/WHEEL
odoo14_addon_account_payment_line_import-14.0.1.0.1.dev8.dist-info/top_level.txt
odoo14_addon_account_payment_line_import-14.0.1.0.1.dev8.dist-info/RECORD
